pelican/plugins/pelican_to_sqlite/__init__.py
pelican/plugins/pelican_to_sqlite/_version.py
pelican/plugins/pelican_to_sqlite/pelican_to_sqlite.py
pelican/plugins/pelican_to_sqlite/test_pelican_to_sqlite.py
pelican_to_sqlite-0.7.0.dist-info/METADATA
pelican_to_sqlite-0.7.0.dist-info/WHEEL
pelican_to_sqlite-0.7.0.dist-info/licenses/LICENSE
pelican_to_sqlite-0.7.0.dist-info/RECORD
