Metadata-Version: 2.4
Name: pelican-to-sqlite
Version: 0.7.0
Summary: A Pelican Plugin for outputting your Pelican posts into a SQLite Database
Project-URL: Issues, https://github.com/ryancheley/pelican-to-sqlite/issues
Project-URL: CI, https://github.com/ryancheley/pelican-to-sqlite/actions
Project-URL: Changelog, https://github.com/ryancheley/pelican-to-sqlite/releases
Author: Ryan Cheley
License: Apache-2.0
License-File: LICENSE
Classifier: Development Status :: 4 - Beta
Requires-Python: >=3.9
Requires-Dist: click
Requires-Dist: html2text
Requires-Dist: pelican
Requires-Dist: sqlite-utils
Provides-Extra: dev
Requires-Dist: packaging; extra == 'dev'
Requires-Dist: ruff; extra == 'dev'
Provides-Extra: docs
Requires-Dist: markdown-include; extra == 'docs'
Requires-Dist: mkdocs; extra == 'docs'
Requires-Dist: mkdocstrings[python]; extra == 'docs'
Provides-Extra: test
Requires-Dist: coverage; extra == 'test'
Requires-Dist: mypy; extra == 'test'
Requires-Dist: pytest; extra == 'test'
